Metadata-Version: 1.2
Name: servicelib
Version: 1.2.0
Summary: Helpers used by the service-layer
Home-page: https://gitlab.com/freemelt/machine-software/servicelib
Author: Freemelt AB
Author-email: opensource@freemelt.com
License: UNKNOWN
Platform: UNKNOWN
Classifier: Environment :: Console
Classifier: Natural Language :: English
Classifier: Programming Language :: Python :: 3
Classifier: Programming Language :: Python :: Implementation :: CPython
Classifier: License :: OSI Approved :: GNU Lesser General Public License v3 (LGPLv3)
Classifier: Operating System :: OS Independent
Requires-Python: >=3.7
